generateStoredProcedure/__init__.py
generateStoredProcedure/backup.py
generateStoredProcedure/compare.py
generateStoredProcedure/login.py
generateStoredProcedure/main.py
gensp-1.0.17.dist-info/METADATA
gensp-1.0.17.dist-info/WHEEL
gensp-1.0.17.dist-info/entry_points.txt
gensp-1.0.17.dist-info/top_level.txt
gensp-1.0.17.dist-info/RECORD
