Metadata-Version: 2.1
Name: gensp
Version: 1.0.17
Summary: 比对postgres数据库备份的数据，得出新增的存储过程
Home-page: https://github.com/zerobyte1o1/gensp
Author: byte
Author-email: liufangjing_byte@163.com
License: UNKNOWN
Platform: UNKNOWN
Classifier: Programming Language :: Python :: 3
Classifier: License :: OSI Approved :: MIT License
Classifier: Operating System :: OS Independent
Requires-Python: >=3
Requires-Dist: psycopg2 (==2.9.6)
Requires-Dist: PyYAML (==6.0)
